sizzlews/__init__.py
sizzlews/__version__.py
sizzlews/client/__init__.py
sizzlews/client/aiohttp.py
sizzlews/client/common.py
sizzlews/client/requests.py
sizzlews/jsonrpc/__init__.py
sizzlews/jsonrpc/manager.py
sizzlews/server/__init__.py
sizzlews/server/annotation.py
sizzlews/server/common.py
sizzlews/server/tornado.py
sizzlews/server/utils.py
sizzlews/server/websockets.py
sizzlews/test/__init__.py
sizzlews/test/aiohttp_client_test.py
sizzlews/test/requests_client_test.py
sizzlews/test/tornado_server_test.py
sizzlews/test/websockets_server_test.py
ws_sizzle-0.0.8.dist-info/METADATA
ws_sizzle-0.0.8.dist-info/WHEEL
ws_sizzle-0.0.8.dist-info/top_level.txt
ws_sizzle-0.0.8.dist-info/RECORD
